Metadata-Version: 2.1
Name: fastapi-redis-cache
Version: 0.2.5
Summary: A simple and robust caching solution for FastAPI endpoints, fueled by the unfathomable power of Redis.
Home-page: https://github.com/a-luna/fastapi-redis-cache
Author: Aaron Luna
Author-email: contact@aaronluna.dev
Maintainer: Aaron Luna
Maintainer-email: contact@aaronluna.dev
License: MIT
Project-URL: Bug Tracker, https://github.com/a-luna/fastapi-redis-cache/issues
Project-URL: Source Code, https://github.com/a-luna/fastapi-redis-cache
Platform: UNKNOWN
Classifier: Development Status :: 4 - Beta
Classifier: Intended Audience :: Developers
Classifier: License :: OSI Approved :: MIT License
Classifier: Natural Language :: English
Classifier: Operating System :: MacOS :: MacOS X
Classifier: Operating System :: POSIX :: Linux
Classifier: Operating System :: Unix
Classifier: Programming Language :: Python :: 3.7
Classifier: Programming Language :: Python :: 3.8
Classifier: Programming Language :: Python :: 3.9
Classifier: Programming Language :: Python :: 3 :: Only
Requires-Python: >=3.7
Provides-Extra: dev
